scsilicon/__init__.py
scsilicon/scsilicon.py
scsilicon/utils.py
scsilicon/version.py
scsilicon/data/normal.profile
SCSilicon-1.1.4.dist-info/LICENSE
SCSilicon-1.1.4.dist-info/METADATA
SCSilicon-1.1.4.dist-info/WHEEL
SCSilicon-1.1.4.dist-info/top_level.txt
SCSilicon-1.1.4.dist-info/RECORD
