Metadata-Version: 2.1
Name: SCSilicon
Version: 1.1.4
Summary: SCSilicon: a Python package that simulate single-cell DNA sequencing data.
Home-page: https://github.com/xikanfeng2/SCSilicon
Author: Xikang Feng
Author-email: fxk@nwpu.edu.cn
License: UNKNOWN
Project-URL: Bug Tracker, https://github.com/xikanfeng2/SCSilicon/issues
Platform: UNKNOWN
Classifier: Programming Language :: Python :: 3
Classifier: License :: OSI Approved :: MIT License
Classifier: Operating System :: OS Independent
Requires-Python: >=3.6
Requires-Dist: numpy (>=1.16.1)
Requires-Dist: pandas (>=0.23.4)
Requires-Dist: tasklogger (>=0.4.0)
Requires-Dist: wget (>=3.2)
Requires-Dist: seaborn (>=0.11.1)
Requires-Dist: matplotlib (>=3.0.2)
